README
setup.py
MeHscr/MeHscr.py
MeHscr/__init__.py
MeHscr.egg-info/PKG-INFO
MeHscr.egg-info/SOURCES.txt
MeHscr.egg-info/dependency_links.txt
MeHscr.egg-info/requires.txt
MeHscr.egg-info/top_level.txt
bin/genome_scr